{"teams":[{"id":26615,"shortname":"what_moves_you","name":"What Moves You","category":"Businesses","image":{"id":1331044,"template_id":1},"whereabouts":"Los Angeles, CA","loan_because":"We believe in supporting others in pursuing their purpose and dreams.","description":"We're here to help you discover your purpose, hone in on your passion &amp; live up to your full potential.","website_url":"www.ginagomez.com","team_since":"2013-04-11T22:40:49Z","membership_type":"open","member_count":1,"loan_count":4,"loaned_amount":100}]}